cgt_calc/__init__.py
cgt_calc/args_parser.py
cgt_calc/const.py
cgt_calc/currency_converter.py
cgt_calc/current_price_fetcher.py
cgt_calc/dates.py
cgt_calc/exceptions.py
cgt_calc/initial_prices.py
cgt_calc/main.py
cgt_calc/model.py
cgt_calc/parsers/__init__.py
cgt_calc/parsers/mssb.py
cgt_calc/parsers/raw.py
cgt_calc/parsers/schwab.py
cgt_calc/parsers/schwab_equity_award_json.py
cgt_calc/parsers/sharesight.py
cgt_calc/parsers/trading212.py
cgt_calc/py.typed
cgt_calc/render_latex.py
cgt_calc/resources/__init__.py
cgt_calc/resources/initial_prices.csv
cgt_calc/resources/template.tex.j2
cgt_calc/spin_off_handler.py
cgt_calc/transaction_log.py
cgt_calc/util.py
cgt_calc-1.13.0.dist-info/WHEEL
cgt_calc-1.13.0.dist-info/LICENSE
cgt_calc-1.13.0.dist-info/entry_points.txt
cgt_calc-1.13.0.dist-info/METADATA
cgt_calc-1.13.0.dist-info/RECORD
