Metadata-Version: 2.1
Name: cgt-calc
Version: 1.13.0
Summary: UK capital gains tax calculator for Charles Schwab and Trading 212 accounts
Home-page: https://github.com/KapJI/capital-gains-calculator
License: MIT
Keywords: capital gain,schwab,trading 212
Author: Ruslan Sayfutdinov
Author-email: ruslan@sayfutdinov.com
Requires-Python: >=3.8,<4.0
Classifier: Development Status :: 3 - Alpha
Classifier: License :: OSI Approved :: MIT License
Classifier: Programming Language :: Python :: 3
Classifier: Programming Language :: Python :: 3.8
Classifier: Programming Language :: Python :: 3.9
Classifier: Programming Language :: Python :: 3.10
Classifier: Programming Language :: Python :: 3.11
Classifier: Programming Language :: Python :: 3.8
Classifier: Topic :: Office/Business :: Financial
Classifier: Typing :: Typed
Requires-Dist: Jinja2 (>=2.11.3,<4.0.0)
Requires-Dist: pandas (>=2.0.3,<3.0.0)
Requires-Dist: requests (>=2.27.1,<3.0.0)
Requires-Dist: types-requests (>=2.27.7,<3.0.0)
Requires-Dist: yfinance (>=0.2.36,<0.3.0)
Project-URL: Bug Tracker, https://github.com/KapJI/capital-gains-calculator/issues
Project-URL: Repository, https://github.com/KapJI/capital-gains-calculator
Project-URL: Release Notes, https://github.com/KapJI/capital-gains-calculator/releases
